<?xml version="1.0" encoding="UTF-8"?>
<mods:mods xmlns:mods="http://www.loc.gov/mods/v3"
           xmlns:xlink="http://www.w3.org/1999/xlink"
           xmlns:xsi="http://www.w3.org/2001/XMLSchema-instance"
           version="3.5"
           xsi:schemaLocation="http://www.loc.gov/mods/v3 http://www.loc.gov/standards/mods/v3/mods-3-5.xsd">
   <mods:identifier type="local">sc153</mods:identifier>
   <mods:titleInfo>
      <mods:title>[Legal] 1802 September, State of Tennessee [to] Sheriff of Cocke County / [witnessed by Francis A. Ramsey]</mods:title>
   </mods:titleInfo>
   <mods:abstract>This is a court order to the sheriff of Cocke County. The sheriff is ordered to bring George H. Hynds to Knoxville. It is witnessed by Francis A. Ramsey.</mods:abstract>
   <mods:originInfo>
      <mods:dateCreated>September 1802</mods:dateCreated>
      <mods:dateCreated encoding="edtf">1802-09</mods:dateCreated>
   </mods:originInfo>
   <mods:subject>
      <mods:topic>Tennessee</mods:topic>
   </mods:subject>
   <mods:subject>
      <mods:topic>Legal document</mods:topic>
   </mods:subject>
   <mods:subject>
      <mods:topic>Court administration</mods:topic>
   </mods:subject>
   <mods:name valueURI="http://id.loc.gov/authorities/names/no2007053135">
      <mods:namePart>Ramsey, Francis A. (Francis Alexander), 1764-1820</mods:namePart>
      <mods:role>
         <mods:roleTerm authority="marcrelator"
                        valueURI="http://id.loc.gov/vocabulary/relators/wit">Witness</mods:roleTerm>
      </mods:role>
   </mods:name>
   <mods:accessCondition type="use and reproduction"
                         xlink:href="http://rightsstatement.org/vocab/CNE/1.0/">Copyright Not Evaluated</mods:accessCondition>
   <mods:location>
      <mods:physicalLocation>University of Tennesse Knoxville. Libraries</mods:physicalLocation>
   </mods:location>
   <mods:relatedItem displayLabel="Project" type="host">
      <mods:titleInfo>
         <mods:title>Tennessee Documentary History</mods:title>
      </mods:titleInfo>
   </mods:relatedItem>
   <mods:relatedItem displayLabel="Collection" type="host">
      <mods:titleInfo>
         <mods:title>Francis A. Ramsey Papers</mods:title>
      </mods:titleInfo>
   </mods:relatedItem>
   <mods:typeOfResource>text</mods:typeOfResource>
   <mods:language>
      <mods:languageTerm type="text" authority="iso639-2b">English</mods:languageTerm>
   </mods:language>
   <mods:recordInfo>
      <mods:recordContentSource>University of Tennesse Knoxville. Libraries</mods:recordContentSource>
      <mods:languageOfCataloging>
         <mods:languageTerm type="code" authority="iso639-2b">eng</mods:languageTerm>
      </mods:languageOfCataloging>
      <mods:recordCreationDate>2020-04-22-04:00</mods:recordCreationDate>
      <mods:recordOrigin>This MODS record was generated into MODS v3.5 from the TEI teiHeader by
          University of Tennessee Libraries Digital Initiatives, using a stylesheet available at
          https://github.com/utkdigitalinitiatives/tei-to-mods.</mods:recordOrigin>
   </mods:recordInfo>
</mods:mods>
